tgram_dnd/__init__.py
tgram_dnd/app.py
tgram_dnd/config.py
tgram_dnd/errors.py
tgram_dnd/utils.py
tgram_dnd/actions/__init__.py
tgram_dnd/actions/action.py
tgram_dnd/actions/raw.py
tgram_dnd/actions/raw_call.py
tgram_dnd/actions/api/__init__.py
tgram_dnd/actions/api/raw.py
tgram_dnd/actions/api/raw_call.py
tgram_dnd/actions/api/methods/__init__.py
tgram_dnd/actions/api/methods/check_subscription.py
tgram_dnd/actions/api/methods/reply.py
tgram_dnd/actions/methods/__init__.py
tgram_dnd/actions/methods/reply.py
tgram_dnd/blocks/__init__.py
tgram_dnd/blocks/callback_block.py
tgram_dnd/blocks/message_block.py
tgram_dnd/caching/__init__.py
tgram_dnd/caching/base.py
tgram_dnd/caching/cached_item.py
tgram_dnd/caching/memory.py
tgram_dnd/conditions/__init__.py
tgram_dnd/conditions/base.py
tgram_dnd/conditions/condition.py
tgram_dnd/enums/__init__.py
tgram_dnd/enums/bot_command_input.py
tgram_dnd/enums/language_codes.py
tgram_dnd/enums/reply.py
tgram_dnd/enums/reply_input.py
tgram_dnd/enums/reply_methods.py
tgram_dnd/flows/__init__.py
tgram_dnd/flows/callback_flow.py
tgram_dnd/flows/message_flow.py
tgram_dnd-0.0.7b0.dist-info/LICENSE
tgram_dnd-0.0.7b0.dist-info/METADATA
tgram_dnd-0.0.7b0.dist-info/WHEEL
tgram_dnd-0.0.7b0.dist-info/top_level.txt
tgram_dnd-0.0.7b0.dist-info/RECORD
