Metadata-Version: 2.1
Name: tgram_dnd
Version: 0.0.7b0
Summary: Tgram Darg-And-Drop helper is a lib to help building DragAndDrop applications, or simply just to make bots faster
Author: SpicyPenguin
License-File: LICENSE
Requires-Dist: jinja2
Requires-Dist: tgram
